creak_sense/__init__.py
creak_sense/predictor.py
creak_sense/upload_to_hf.py
creak_sense/utils.py
creak_sense-0.0.4.dist-info/METADATA
creak_sense-0.0.4.dist-info/WHEEL
creak_sense-0.0.4.dist-info/top_level.txt
creak_sense-0.0.4.dist-info/RECORD
