Metadata-Version: 2.1
Name: creak-sense
Version: 0.0.4
Summary: Tests whether a sentence is consistent with the CREAK dataset.
Home-page: http://github.com/fractalego/creak_sense
Author: Alberto Cetoli
Author-email: alberto@fractalego.io
License: UNKNOWN
Platform: UNKNOWN
Classifier: License :: OSI Approved :: MIT License
Requires-Dist: transformers (>=4.17.0)
Requires-Dist: sentence-transformers (>=2.0.0)
Requires-Dist: torch (>=1.9.0)
